doubtlab/__init__.py
doubtlab/benchmark.py
doubtlab/ensemble.py
doubtlab/reason.py
doubtlab-0.2.4.dist-info/LICENSE
doubtlab-0.2.4.dist-info/METADATA
doubtlab-0.2.4.dist-info/WHEEL
doubtlab-0.2.4.dist-info/top_level.txt
doubtlab-0.2.4.dist-info/RECORD
