Metadata-Version: 2.1
Name: doubtlab
Version: 0.2.4
Summary: Don't Blindly Trust Your Labels
Home-page: https://koaning.github.io/doubtlab/
Author: Vincent D. Warmerdam
License: UNKNOWN
Project-URL: Documentation, https://koaning.github.io/doubtlab/
Project-URL: Source Code, https://github.com/koaning/doubtlab/
Project-URL: Issue Tracker, https://github.com/koaning/doubtlab/issues
Platform: UNKNOWN
Classifier: Intended Audience :: Science/Research
Classifier: Programming Language :: Python :: 3
Classifier: Programming Language :: Python :: 3.7
Classifier: Programming Language :: Python :: 3.8
Classifier: Programming Language :: Python :: 3.9
Classifier: License :: OSI Approved :: MIT License
Classifier: Topic :: Scientific/Engineering
Classifier: Topic :: Scientific/Engineering :: Artificial Intelligence
License-File: LICENSE
Requires-Dist: scikit-learn (>=1.0.0)
Requires-Dist: cleanlab (>=2.0)
Requires-Dist: pandas (>=1.3.3)
Provides-Extra: dev
Requires-Dist: scikit-learn (>=1.0.0) ; extra == 'dev'
Requires-Dist: cleanlab (>=2.0) ; extra == 'dev'
Requires-Dist: pandas (>=1.3.3) ; extra == 'dev'
Requires-Dist: mkdocs (==1.3.0) ; extra == 'dev'
Requires-Dist: mkdocs-material (==4.6.3) ; extra == 'dev'
Requires-Dist: mkdocstrings (==0.18.1) ; extra == 'dev'
Requires-Dist: mktestdocs (==0.1.2) ; extra == 'dev'
Requires-Dist: mkdocstrings-python (==0.6.6) ; extra == 'dev'
Requires-Dist: interrogate (>=1.5.0) ; extra == 'dev'
Requires-Dist: flake8 (>=3.6.0) ; extra == 'dev'
Requires-Dist: pytest (>=4.0.2) ; extra == 'dev'
Requires-Dist: black (>=19.3b0) ; extra == 'dev'
Requires-Dist: pre-commit (>=2.2.0) ; extra == 'dev'
Requires-Dist: flake8-print (>=4.0.0) ; extra == 'dev'
Requires-Dist: whatlies (==0.6.4) ; extra == 'dev'
